pxr/.libs/libPxrTs.dylib
pxr/Ts/__init__.py
pxr/Ts/_ts.so
pxr_ts-25.8.dist-info/METADATA
pxr_ts-25.8.dist-info/WHEEL
pxr_ts-25.8.dist-info/licenses/NOTICE.txt
pxr_ts-25.8.dist-info/licenses/LICENSE.txt
pxr_ts-25.8.dist-info/RECORD
